{
  "objectInfo" : {
    "id" : "0nXn5QcVoXedE2uFRNoPMm",
    "name" : "fwff_I0065",
    "type" : "FWCONFIG",
    "metadata" : {
      "modelVersion" : {
        "major" : 0,
        "minor" : 0
      },
      "repoInfo" : {
        "repoHandle" : "001KD629000000000004"
      },
      "contextAttributes" : [ {
        "name" : "id",
        "value" : "@1"
      } ],
      "additionalInfo" : {
        "description" : "PIM process",
        "contentType" : "JSON",
        "documentState" : "VALID"
      }
    }
  },
  "dataFileExtension" : "zip",
  "objectRefs" : [ ]
}